odoo9_addon_purchase_request_department-9.0.1.0.0.99.dev6-py2.7-nspkg.pth
odoo9_addon_purchase_request_department-9.0.1.0.0.99.dev6.dist-info/METADATA
odoo9_addon_purchase_request_department-9.0.1.0.0.99.dev6.dist-info/RECORD
odoo9_addon_purchase_request_department-9.0.1.0.0.99.dev6.dist-info/WHEEL
odoo9_addon_purchase_request_department-9.0.1.0.0.99.dev6.dist-info/namespace_packages.txt
odoo9_addon_purchase_request_department-9.0.1.0.0.99.dev6.dist-info/top_level.txt
odoo_addons/purchase_request_department/README.rst
odoo_addons/purchase_request_department/__init__.py
odoo_addons/purchase_request_department/__openerp__.py
odoo_addons/purchase_request_department/hooks.py
odoo_addons/purchase_request_department/i18n/de.po
odoo_addons/purchase_request_department/i18n/es.po
odoo_addons/purchase_request_department/i18n/fr.po
odoo_addons/purchase_request_department/i18n/hr.po
odoo_addons/purchase_request_department/i18n/it.po
odoo_addons/purchase_request_department/i18n/nb.po
odoo_addons/purchase_request_department/i18n/nb_NO.po
odoo_addons/purchase_request_department/i18n/pt_BR.po
odoo_addons/purchase_request_department/i18n/sl.po
odoo_addons/purchase_request_department/i18n/tr.po
odoo_addons/purchase_request_department/models/__init__.py
odoo_addons/purchase_request_department/models/purchase_request.py
odoo_addons/purchase_request_department/static/description/icon.png
odoo_addons/purchase_request_department/tests/__init__.py
odoo_addons/purchase_request_department/tests/test_purchase_request_department.py
odoo_addons/purchase_request_department/views/purchase_request_department_view.xml
